LICENSE
MANIFEST.in
README.md
setup.py
Pfunboost.egg-info/PKG-INFO
Pfunboost.egg-info/SOURCES.txt
Pfunboost.egg-info/dependency_links.txt
Pfunboost.egg-info/requires.txt
Pfunboost.egg-info/top_level.txt
funboost/__init__.py
funboost/constant.py
funboost/funboost_config_deafult.py
funboost/helpers.py
funboost/set_frame_config.py
funboost/assist/user_custom_broker_register.py
funboost/beggar_version_implementation/beggar_redis_consumer.py
funboost/concurrent_pool/__init__.py
funboost/concurrent_pool/async_helper.py
funboost/concurrent_pool/async_pool_executor.py
funboost/concurrent_pool/bounded_processpoolexcutor_gt_py37.py
funboost/concurrent_pool/bounded_processpoolexcutor_py36.py
funboost/concurrent_pool/bounded_threadpoolexcutor.py
funboost/concurrent_pool/concurrent_pool_with_multi_process.py
funboost/concurrent_pool/custom_evenlet_pool_executor.py
funboost/concurrent_pool/custom_gevent_pool_executor.py
funboost/concurrent_pool/custom_threadpool_executor.py
funboost/concurrent_pool/custom_threadpool_executor000.py
funboost/concurrent_pool/single_thread_executor.py
funboost/consumers/__init__.py
funboost/consumers/base_consumer.py
funboost/consumers/confirm_mixin.py
funboost/consumers/http_consumer.py
funboost/consumers/http_consumer000.py
funboost/consumers/httpsqs_consumer.py
funboost/consumers/kafka_consumer.py
funboost/consumers/kafka_consumer_manually_commit.py
funboost/consumers/kombu_consumer.py
funboost/consumers/local_python_queue_consumer.py
funboost/consumers/mongomq_consumer.py
funboost/consumers/mqtt_consumer.py
funboost/consumers/nats_consumer.py
funboost/consumers/nsq_consumer.py
funboost/consumers/peewee_conusmer.py
funboost/consumers/persist_queue_consumer.py
funboost/consumers/rabbitmq_amqpstorm_consumer.py
funboost/consumers/rabbitmq_pika_consumer.py
funboost/consumers/rabbitmq_pika_consumerv0.py
funboost/consumers/rabbitmq_rabbitpy_consumer.py
funboost/consumers/redis_brpoplpush_consumer.py
funboost/consumers/redis_consumer.py
funboost/consumers/redis_consumer_ack_able.py
funboost/consumers/redis_consumer_simple.py
funboost/consumers/redis_filter.py
funboost/consumers/redis_stream_consumer.py
