Metadata-Version: 2.1
Name: Pfunboost
Version: 17.2
Summary: funboost  is function scheduling distributed framework,support threading,gevent,eventlet,asyncio concurrent,support all kinds of message queue,and has manay control way
Home-page: https://github.com/ydf0509/funboost
Author: bfzs
Author-email: ydf0509@sohu.com
Maintainer: ydf
Maintainer-email: ydf0509@sohu.com
License: BSD License
Keywords: funboost,distributed-framework,function-scheduling,rabbitmq,rocketmq,kafka,nsq,redis,disk,sqlachemy,consume-confirm,timing,task-scheduling,apscheduler,pulsar,mqtt,kombu
Platform: all
Classifier: Development Status :: 4 - Beta
Classifier: Operating System :: OS Independent
Classifier: Intended Audience :: Developers
Classifier: License :: OSI Approved :: BSD License
Classifier: Programming Language :: Python
Classifier: Programming Language :: Python :: Implementation
Classifier: Programming Language :: Python :: 3.6
Classifier: Programming Language :: Python :: 3.7
Classifier: Programming Language :: Python :: 3.8
Classifier: Programming Language :: Python :: 3.9
Classifier: Topic :: Software Development :: Libraries
License-File: LICENSE
